kybonet/__init__.py
kybonet/client.py
kybonet/config.yml
kybonet/crypto.py
kybonet/input_devices.py
kybonet/server.py
kybonet-0.0.9.dist-info/LICENSE.txt
kybonet-0.0.9.dist-info/METADATA
kybonet-0.0.9.dist-info/WHEEL
kybonet-0.0.9.dist-info/entry_points.txt
kybonet-0.0.9.dist-info/top_level.txt
kybonet-0.0.9.dist-info/RECORD
